utils/saturation/CONTROL_LED.v
/*
Módulo que realiza o controle de saturação de um registrador de 16 bits
    
    led_g é acionado quando o reg está em seu valor máximo
    led_r é acionado quando o reg está em seu valor mínimo

*/
module CONTROL_LED #(parameter width = 4)
                    (input[width:0] regs, output led_r, output led_g);

    assign led_g = (regs == {(width + 1){1'b1}});
    assign led_r = (regs == {(width + 1){1'b0}});

endmodule

utils/saturation_test/SATURATION.v
/*
Módulo que realiza o controle de saturação de um registrador de 16 bits
*/
module SATURATION #(parameter width = 4)
                    (input clk, input increase, input decrease, output reg[width:0] register);

    initial begin
        register = {(width+1){1'b0}};
    end

    always @(posedge clk) begin

        // Se for incrementar e não estiver no limite superior
        if (increase & (register != {(width+1){1'b1}})) begin
            register = register + 1'b1;
        end
        // Se for decrementar e não estiver no limite inferior
        else if (decrease & (register != {(width+1){1'b0}})) begin
            register = register - 1'b1;
        end
        else begin
            register = register;
        end

        // if (increase) begin
        //     // Se já estiver no limite superior, não faça nada
        //     if (register == {(width){1'b1}}) begin
        //         register = register;
        //     end
        //     // Se ainda não estiver no limite superior, some 1 ao valor
        //     else begin
        //         register = register + 1'b1;
        //     end
        // end

        // else if (decrease) begin
        //     // Se já estiver no limite inferior, não faça nada
        //     if (register == 16'b0) begin
        //         register = 16'b0;
        //     end
        //     // Se ainda não estiver no limite inferior, subtrai 1 do valor
        //     else begin
        //         register = register - 1'b1;
        //     end
        // end
        // else begin
        //     register = register;
        // end
    end


endmodule

utils/saturation/DEBOUNCE.v
// Módulo para tratar o bouncing dos botões com MEF de Moore
module DEBOUNCE(CLK_FPGA, Btn, Pulse);
	input CLK_FPGA, Btn;
	output Pulse;
	
	reg [1:0] state, nextstate;
	
	parameter A =2'b00;
	parameter B =2'b01;
	parameter C =2'b10;
	

	
	// state register
	always @ ( posedge CLK_FPGA)	
		state <= nextstate ;
		
	// next state logic
	always @ (*)
		case ( state )
			A : if ( Btn ) nextstate <= B ;
			else nextstate <= A ;
			B : if ( Btn ) nextstate <= C ;
			else nextstate <= A ;
			C : if ( Btn ) nextstate <= C ;
			else nextstate <= A ;
			default : nextstate <= A ;
			
		endcase
		
	// output logic
	assign Pulse = ( state == B ) ;
	endmodule

utils/saturation_test/MAIN.v
/* 
Módulo para realizar a saturação de um reg de 16 bits e acionar leds quando estiver nos extremos
*/
module MAIN #(parameter width = 4 )
(input clk, input btn1, input btn2, output led_r, output led_g );

    wire pulse_increase, pulse_decrease;

    wire[width:0] regs_w;

    DEBOUNCE debounce_increase_btn(clk, btn1, pulse_increase);
    DEBOUNCE debounce_decrease_btn(clk, btn2, pulse_decrease);

    SATURATION #(.width(width)) saturation(clk, pulse_increase, pulse_decrease, regs_w);

    CONTROL_LED #(.width(width)) control_output(regs_w, led_r, led_g);

endmodule

utils/saturation_test/main_icarus_tb.v
module test;
    reg btn1 = 1;
    reg btn2 = 0;
    reg clk = 0;

    wire led_r, led_g;

    integer i=0;// Variável para controle dos sinais de entrada gerados

    // Inserindo as formas de onda dos sinais de entrada
    initial begin
        $dumpfile("test.vcd");
        $dumpvars(0, test);

        /*== Loop para fazer o wave do botão de incremento ==*/ 
        for (i = 0; i<2;i++ ) begin
            # 5 btn1 = 0;
            # 10 btn1 = 1;
        end
        # 5 btn1 = 0;

        /*== Loop para fazer o wave do botão de decremento ==*/ 
        for (i = 0; i<3;i++ ) begin
            # 5 btn2 = 0;
            # 10 btn2 = 1;
        end

        /* Encerro a simulação no tempo 513 */
        # 513 $finish;
    end

    always #1 clk = ~clk;

    MAIN #(.width(1)) mod_main(clk, btn1, btn2, led_r, led_g);

    //wire [1:0] register;
    //SATURATION #(.width(1)) saturation(clk, btn1, btn2, register);

endmodule

utils/saturation_test/test.vcd
$date
	Sat Mar 02 14:45:35 2024
$end
$version
	Icarus Verilog
$end
$timescale
	1s
$end
$scope module test $end
$var wire 1 ! led_r $end
$var wire 1 " led_g $end
$var reg 1 # btn1 $end
$var reg 1 $ btn2 $end
$var reg 1 % clk $end
$var integer 32 & i [31:0] $end
$scope module mod_main $end
$var wire 1 # btn1 $end
$var wire 1 $ btn2 $end
$var wire 1 % clk $end
$var wire 2 ' regs_w [1:0] $end
$var wire 1 ( pulse_increase $end
$var wire 1 ) pulse_decrease $end
$var wire 1 ! led_r $end
$var wire 1 " led_g $end
$scope module control_output $end
$var wire 2 * regs [1:0] $end
$var wire 1 ! led_r $end
$var wire 1 " led_g $end
$upscope $end
$scope module debounce_decrease_btn $end
$var wire 1 $ Btn $end
$var wire 1 % CLK_FPGA $end
$var wire 1 ) Pulse $end
$var reg 2 + nextstate [1:0] $end
$var reg 2 , state [1:0] $end
$upscope $end
$scope module debounce_increase_btn $end
$var wire 1 # Btn $end
$var wire 1 % CLK_FPGA $end
$var wire 1 ( Pulse $end
$var reg 2 - nextstate [1:0] $end
$var reg 2 . state [1:0] $end
$upscope $end
$scope module saturation $end
$var wire 1 % clk $end
$var wire 1 ) decrease $end
$var wire 1 ( increase $end
$var reg 2 / register [1:0] $end
$upscope $end
$upscope $end
$upscope $end
$enddefinitions $end
#0
$dumpvars
b0 /
bx .
b0 -
bx ,
b0 +
b0 *
x)
x(
b0 '
b0 &
0%
0$
1#
0"
1!
$end
#1
b1 -
0(
b0 .
0)
b0 ,
1%
#2
0%
#3
b10 -
1(
b1 .
1%
#4
0%
#5
0(
b10 .
b0 -
0!
b1 '
b1 *
b1 /
1%
0#
#6
0%
#7
b0 .
1%
#8
0%
#9
1%
#10
0%
#11
1%
#12
0%
#13
1%
#14
0%
#15
b1 -
1%
b1 &
1#
#16
0%
#17
b10 -
1(
b1 .
1%
#18
0%
#19
0(
b10 .
b10 '
b10 *
b10 /
1%
#20
b0 -
0%
0#
#21
b0 .
1%
#22
0%
#23
1%
#24
0%
#25
1%
#26
0%
#27
1%
#28
0%
#29
1%
#30
b1 -
0%
b10 &
1#
#31
b10 -
1(
b1 .
1%
#32
0%
#33
0(
b10 .
1"
b11 '
b11 *
b11 /
1%
#34
0%
#35
b0 -
1%
b0 &
0#
#36
0%
#37
b0 .
1%
#38
0%
#39
1%
#40
0%
#41
1%
#42
0%
#43
1%
#44
0%
#45
1%
#46
0%
#47
1%
#48
0%
#49
1%
#50
b1 +
0%
b1 &
1$
#51
b10 +
1)
b1 ,
1%
#52
0%
#53
0)
b10 ,
0"
b10 '
b10 *
b10 /
1%
#54
0%
#55
b0 +
1%
0$
#56
0%
#57
b0 ,
1%
#58
0%
#59
1%
#60
0%
#61
1%
#62
0%
#63
1%
#64
0%
#65
b1 +
1%
b10 &
1$
#66
0%
#67
b10 +
1)
b1 ,
1%
#68
0%
#69
0)
b10 ,
b1 '
b1 *
b1 /
1%
#70
b0 +
0%
0$
#71
b0 ,
1%
#72
0%
#73
1%
#74
0%
#75
1%
#76
0%
#77
1%
#78
0%
#79
1%
#80
b1 +
0%
b11 &
1$
#81
b10 +
1)
b1 ,
1%
#82
0%
#83
0)
b10 ,
1!
b0 '
b0 *
b0 /
1%
